coeus_appium/__init__.py
coeus_appium/android_keycodes.py
coeus_appium/appium_driver.py
coeus_appium/ios_keycodes.py
coeus_test_appium-0.1.10.dist-info/LICENSE
coeus_test_appium-0.1.10.dist-info/METADATA
coeus_test_appium-0.1.10.dist-info/WHEEL
coeus_test_appium-0.1.10.dist-info/top_level.txt
coeus_test_appium-0.1.10.dist-info/RECORD
